jmarkov/__init__.py
jmarkov/ctbd.py
jmarkov/ctmc.py
jmarkov/dtmc.py
jmarkov/finite_ctbd.py
jmarkov/markov_chain.py
jmarkov/mdp/__init__.py
jmarkov/mdp/dtmdp.py
jmarkov/phase/__init__.py
jmarkov/phase/ctph.py
jmarkov/phase/dtph.py
jmarkov/phase/fit/__init__.py
jmarkov/phase/fit/moments_ctph2.py
jmarkov/queue/__init__.py
jmarkov/queue/gginf.py
jmarkov/queue/mg1.py
jmarkov/queue/mmk.py
jmarkov/queue/mmkn.py
jmarkov/queue/phph1.py
jmarkov/sdp/__init__.py
jmarkov/sdp/dtsdp.py
jmarkov-0.3.9.dist-info/METADATA
jmarkov-0.3.9.dist-info/WHEEL
jmarkov-0.3.9.dist-info/licenses/LICENSE
jmarkov-0.3.9.dist-info/RECORD
