Metadata-Version: 2.4
Name: jmarkov
Version: 0.3.9
Summary: A python package for Markov chain modeling
Project-URL: homepage, https://github.com/copa-uniandes/jmarkov
Project-URL: documentation, https:/https://jmarkov.readthedocs.io/en/latest/
Project-URL: source, https://github.com/copa-uniandes/jmarkov
Project-URL: download, https://pypi.org/project/jmarkov/
Project-URL: tracker, https://github.com/copa-uniandes/jmarkov/issues
Author-email: Juan F Perez <juanfernando.perez@gmail.com>, Maria-Gabriela Urango <m.urango@uniandes.edu.co>
License-File: LICENSE
Classifier: License :: OSI Approved :: MIT License
Classifier: Operating System :: OS Independent
Classifier: Programming Language :: Python :: 3
Requires-Python: >=3.8
Requires-Dist: numpy
Requires-Dist: scipy
Requires-Dist: typing
